<?xml version="1.0" standalone="no"?>
<?xml-stylesheet type="text/xsl" href="file:///C:/Analog Devices/CrossCore Embedded Studio 2.2.0/System/linker_log.xsl"?>
<DOCUMENT gen_time='Mon Aug 08 03:31:25 2016
'>
<MSG id='0460C0E8' mid='li3050' type='Informational' suppressed=''>
<TEXT><![CDATA[Input section(s) were excluded from output section 'dxe_block0_nw_code']]></TEXT>
<EXTENDED_INFO><![CDATA[The following input section(s) were excluded
    app_startup.doj(seg_pmco)
    app_startup.doj(seg_pmco)
    .\src\processing.doj(seg_pmco)
    .\src\sport1_isr_process_samples.doj(seg_pmco)
    libcc.dlb[divrem_s32.doj](seg_pmco)
    libcc.dlb[divrem_s64.doj](seg_pmco)
    libcc.dlb[divrem_u32.doj](seg_pmco)
    libcc.dlb[divrem_u64.doj](seg_pmco)
    libcc.dlb[float_divide.doj](seg_pmco)
    libcc.dlb[flt_sprt.doj](seg_pmco)
    libcc.dlb[lib_ldtof.doj](seg_pmco)
    libcc.dlb[memcpy.doj](seg_pmco)
    libcc.dlb[strlen.doj](seg_pmco)
    libc.dlb[adi_fatal_error.doj](seg_pmco)
    libc.dlb[asinf.doj](seg_pmco)
    libc.dlb[atanf.doj](seg_pmco)
    libc.dlb[dispatched_handler_activate.doj](seg_pmco)
    libc.dlb[dispatched_handler_deactivate.doj](seg_pmco)
    libc.dlb[dispatched_handler_register.doj](seg_pmco)
    libc.dlb[dispatched_handler_unregister.doj](seg_pmco)
    libc.dlb[int_dispatcher_214xx.doj](seg_pmco)
    libc.dlb[isinff.doj](seg_pmco)
    libc.dlb[modff.doj](seg_pmco)
    libc.dlb[no_dispatched_handler.doj](seg_pmco)
    libc.dlb[powf.doj](seg_pmco)
    libc.dlb[raise_interrupt.doj](seg_pmco)
    libc.dlb[set_c.doj](seg_pmco)
    libc.dlb[sinf.doj](seg_pmco)
    libc.dlb[sqrtf.doj](seg_pmco)
    libdsp.dlb[bitrev_simd.doj](seg_pmco)
    libdsp.dlb[cfft1024_simd.doj](seg_pmco)
    libdsp.dlb[cfftmag_simd.doj](seg_pmco)
    libdsp.dlb[cmatmmlt.doj](seg_pmco)
    libdsp.dlb[conjf.doj](seg_pmco)
    libdsp.dlb[convolve.doj](seg_pmco)
    libdsp.dlb[csubf.doj](seg_pmco)
    libdsp.dlb[matmul.doj](seg_pmco)
    libdsp.dlb[mattransp.doj](seg_pmco)]]></EXTENDED_INFO>
</MSG>
<MSG id='045EABC0' mid='li3050' type='Informational' suppressed=''>
<TEXT><![CDATA[Input section(s) were excluded from output section 'dxe_block0_nw_code_prio1']]></TEXT>
<EXTENDED_INFO><![CDATA[The following input section(s) were excluded
    libcc.dlb[memcpy.doj](seg_pmco)
    libc.dlb[adi_fatal_error.doj](seg_pmco)
    libc.dlb[asinf.doj](seg_pmco)
    libc.dlb[atanf.doj](seg_pmco)
    libc.dlb[int_dispatcher_214xx.doj](seg_pmco)
    libc.dlb[isinff.doj](seg_pmco)
    libc.dlb[modff.doj](seg_pmco)
    libc.dlb[powf.doj](seg_pmco)
    libc.dlb[set_c.doj](seg_pmco)
    libc.dlb[sinf.doj](seg_pmco)
    libc.dlb[sqrtf.doj](seg_pmco)
    libdsp.dlb[bitrev_simd.doj](seg_pmco)
    libdsp.dlb[cfft1024_simd.doj](seg_pmco)
    libdsp.dlb[cfftmag_simd.doj](seg_pmco)
    libdsp.dlb[cmatmmlt.doj](seg_pmco)
    libdsp.dlb[conjf.doj](seg_pmco)
    libdsp.dlb[convolve.doj](seg_pmco)
    libdsp.dlb[csubf.doj](seg_pmco)
    libdsp.dlb[matmul.doj](seg_pmco)
    libdsp.dlb[mattransp.doj](seg_pmco)]]></EXTENDED_INFO>
</MSG>
<MSG id='0460C2B8' mid='li3050' type='Informational' suppressed=''>
<TEXT><![CDATA[Input section(s) were excluded from output section 'dxe_block0_nw_code_prio3']]></TEXT>
<EXTENDED_INFO><![CDATA[The following input section(s) were excluded
    app_startup.doj(seg_pmco)
    app_startup.doj(seg_pmco)
    .\src\processing.doj(seg_pmco)
    .\src\sport1_isr_process_samples.doj(seg_pmco)
    libcc.dlb[divrem_s32.doj](seg_pmco)
    libcc.dlb[divrem_s64.doj](seg_pmco)
    libcc.dlb[divrem_u32.doj](seg_pmco)
    libcc.dlb[divrem_u64.doj](seg_pmco)
    libcc.dlb[float_divide.doj](seg_pmco)
    libcc.dlb[flt_sprt.doj](seg_pmco)
    libcc.dlb[lib_ldtof.doj](seg_pmco)
    libcc.dlb[memcpy.doj](seg_pmco)
    libcc.dlb[strlen.doj](seg_pmco)
    libc.dlb[adi_fatal_error.doj](seg_pmco)
    libc.dlb[asinf.doj](seg_pmco)
    libc.dlb[atanf.doj](seg_pmco)
    libc.dlb[dispatched_handler_activate.doj](seg_pmco)
    libc.dlb[dispatched_handler_deactivate.doj](seg_pmco)
    libc.dlb[dispatched_handler_register.doj](seg_pmco)
    libc.dlb[dispatched_handler_unregister.doj](seg_pmco)
    libc.dlb[int_dispatcher_214xx.doj](seg_pmco)
    libc.dlb[isinff.doj](seg_pmco)
    libc.dlb[modff.doj](seg_pmco)
    libc.dlb[no_dispatched_handler.doj](seg_pmco)
    libc.dlb[powf.doj](seg_pmco)
    libc.dlb[raise_interrupt.doj](seg_pmco)
    libc.dlb[set_c.doj](seg_pmco)
    libc.dlb[sinf.doj](seg_pmco)
    libc.dlb[sqrtf.doj](seg_pmco)
    libdsp.dlb[bitrev_simd.doj](seg_pmco)
    libdsp.dlb[cfft1024_simd.doj](seg_pmco)
    libdsp.dlb[cfftmag_simd.doj](seg_pmco)
    libdsp.dlb[cmatmmlt.doj](seg_pmco)
    libdsp.dlb[conjf.doj](seg_pmco)
    libdsp.dlb[convolve.doj](seg_pmco)
    libdsp.dlb[csubf.doj](seg_pmco)
    libdsp.dlb[matmul.doj](seg_pmco)
    libdsp.dlb[mattransp.doj](seg_pmco)]]></EXTENDED_INFO>
</MSG>
<MSG id='0460C3A8' mid='li3050' type='Informational' suppressed=''>
<TEXT><![CDATA[Input section(s) were excluded from output section 'dxe_sdram_nw_code']]></TEXT>
<EXTENDED_INFO><![CDATA[The following input section(s) were excluded
    app_startup.doj(seg_pmco)
    app_startup.doj(seg_pmco)
    .\src\processing.doj(seg_pmco)
    .\src\sport1_isr_process_samples.doj(seg_pmco)
    libcc.dlb[divrem_s32.doj](seg_pmco)
    libcc.dlb[divrem_s64.doj](seg_pmco)
    libcc.dlb[divrem_u32.doj](seg_pmco)
    libcc.dlb[divrem_u64.doj](seg_pmco)
    libcc.dlb[float_divide.doj](seg_pmco)
    libcc.dlb[flt_sprt.doj](seg_pmco)
    libcc.dlb[lib_ldtof.doj](seg_pmco)
    libcc.dlb[memcpy.doj](seg_pmco)
    libcc.dlb[strlen.doj](seg_pmco)
    libc.dlb[adi_fatal_error.doj](seg_pmco)
    libc.dlb[asinf.doj](seg_pmco)
    libc.dlb[atanf.doj](seg_pmco)
    libc.dlb[dispatched_handler_activate.doj](seg_pmco)
    libc.dlb[dispatched_handler_deactivate.doj](seg_pmco)
    libc.dlb[dispatched_handler_register.doj](seg_pmco)
    libc.dlb[dispatched_handler_unregister.doj](seg_pmco)
    libc.dlb[int_dispatcher_214xx.doj](seg_pmco)
    libc.dlb[isinff.doj](seg_pmco)
    libc.dlb[modff.doj](seg_pmco)
    libc.dlb[no_dispatched_handler.doj](seg_pmco)
    libc.dlb[powf.doj](seg_pmco)
    libc.dlb[raise_interrupt.doj](seg_pmco)
    libc.dlb[set_c.doj](seg_pmco)
    libc.dlb[sinf.doj](seg_pmco)
    libc.dlb[sqrtf.doj](seg_pmco)
    libdsp.dlb[bitrev_simd.doj](seg_pmco)
    libdsp.dlb[cfft1024_simd.doj](seg_pmco)
    libdsp.dlb[cfftmag_simd.doj](seg_pmco)
    libdsp.dlb[cmatmmlt.doj](seg_pmco)
    libdsp.dlb[conjf.doj](seg_pmco)
    libdsp.dlb[convolve.doj](seg_pmco)
    libdsp.dlb[csubf.doj](seg_pmco)
    libdsp.dlb[matmul.doj](seg_pmco)
    libdsp.dlb[mattransp.doj](seg_pmco)]]></EXTENDED_INFO>
</MSG>
</DOCUMENT>
